{
  "title": "2202598_군인복지기본법_일부개정법률안",
  "bill_number": "2598",
  "proposal_date": "2024. 8. 6.",
  "submission_date": "",
  "is_alternative": false,
  "alternative_bill_numbers": [],
  "has_comparison_table": false,
  "comparison_table": "신·구조문대비표\n현 행 개 정 안\n제9조(군 숙소 지원 등) ① 국가 제9조(군 숙소 지원 등) ① ----\n는 군인이 안정된 주거생활을 -------------------------\n함으로써 근무에 전념할 수 있 -------------------------\n도록 하기 위하여 군인(지원에 -------------------------\n의하지 아니하고 임용된 부사 -------------------------\n관 및 병을 제외한다. 이하 이 -------------------------\n조 및 제10조에서 같다)에게 -------------------------\n다음 각 호의 어느 하나에 해 -------------------------\n당하는 주거지원을 제공하여야 -------------------------\n한다. 다만, 제2호에 해당하는 ----. -------------------\n주거지원은 관사를 제공받지 ---------군 숙소를 제공받지\n못한 군인에 한하여 제공한다. 못한 군인에--------------.\n1. 관사 또는 독신자숙소(이하 1. 관사 또는 간부숙소-------\n이 조에서 “군 숙소”라 한다) -----------------------\n2. (생 략) 2. (현행과 같음)\n② ∼ ④ (생 략) ② ∼ ④ (현행과 같음)",
  "full_text": "군인복지기본법 일부개정법률안\n(김병주의원 대표발의)\n발의연월일 : 2024. 8. 6.\n의 안\n2598\n번 호 발 의 자 : 김병주ㆍ민병덕ㆍ정성호\n윤후덕ㆍ허 영ㆍ정동영\n임오경ㆍ위성락ㆍ박지원\n안규백ㆍ김준혁ㆍ정청래\n이성윤 의원(13인)\n제안이유 및 주요내용\n현행법은 군인이 안정된 주거생활을 함으로써 근무에 전념할 수 있\n도록 군인에게 군 숙소인 관사(부양가족이 있는 경우) 또는 간부숙소\n(부양가족이 없는 군인)와 같은 주거지원을 제공하도록 규정하고 있\n음.\n그런데 부양가족이 없는 초급간부 등의 경우에는 관사 입주자격이\n없기에 주로 간부숙소에 입주하며, 만약 간부숙소가 없거나 부족한 경\n우에는 개인부담으로 전ㆍ월세 자금을 마련하여 거주하는 실정임.\n이에 간부숙소 부족으로 주거지원을 받지 못하는 초급간부 등에게\n전ㆍ월세를 지원받게 하도록 관련 규정을 개정해 주거지원 사각지대\n를 해소하고자 함.\n또한 현행 「군인복지기본법」 제9조제1항제1호에 군 숙소를 ‘관사\n또는 독신자숙소’로 규정하고 있음. 독신자숙소에서 ‘독신’은 배우자가\n\n\n\n없는 사람을 지칭하는 것임. 그러나 기혼자 중 근무지가 원거리로 인\n해 가족과 떨어져 사는 군인의 경우 독신이 아님에도 독신자숙소에\n거주하기 때문에 ‘기혼독신자숙소’라는 명칭으로 운영해왔음.\n‘미혼’, ‘기혼’, ‘독신’이라는 명칭을 혼합해 사용해온 모순을 해소하기\n위해 지난 2009년 「국방ㆍ군사시설기준」에서 사용되던 ‘독신자숙소’\n는 ‘간부숙소’로 명칭이 수정된 바 있음. 또한, 군인 주거지원 관련 훈\n령인 「군 주거지원 사업 운영 훈령」에서는 2014년부터 독신숙소를\n간부숙소로 변경해 운영해왔음.\n따라서 이에 맞춰 군 주거지원의 근거법령인 「군인복지기본법」에\n규정되어 있는 독신자숙소를 간부숙소로 용어를 수정하고자 함(안 제9\n조제1항).\n\n법률 제 호\n군인복지기본법 일부개정법률안\n군인복지기본법 일부를 다음과 같이 개정한다.\n제9조제1항 각 호 외의 부분 단서 중 “관사를 제공받지 못한 군인에”\n를 “군 숙소를 제공받지 못한 군인에”로 하고, 같은 항 제1호 중 “관\n사 또는 독신자숙소”를 “관사 또는 간부숙소”로 한다.\n부 칙\n이 법은 2025년 1월 1일부터 시행한다.\n\n\n\n\n신·구조문대비표\n현 행 개 정 안\n제9조(군 숙소 지원 등) ① 국가 제9조(군 숙소 지원 등) ① ----\n는 군인이 안정된 주거생활을 -------------------------\n함으로써 근무에 전념할 수 있 -------------------------\n도록 하기 위하여 군인(지원에 -------------------------\n의하지 아니하고 임용된 부사 -------------------------\n관 및 병을 제외한다. 이하 이 -------------------------\n조 및 제10조에서 같다)에게 -------------------------\n다음 각 호의 어느 하나에 해 -------------------------\n당하는 주거지원을 제공하여야 -------------------------\n한다. 다만, 제2호에 해당하는 ----. -------------------\n주거지원은 관사를 제공받지 ---------군 숙소를 제공받지\n못한 군인에 한하여 제공한다. 못한 군인에--------------.\n1. 관사 또는 독신자숙소(이하 1. 관사 또는 간부숙소-------\n이 조에서 “군 숙소”라 한다) -----------------------\n2. (생 략) 2. (현행과 같음)\n② ∼ ④ (생 략) ② ∼ ④ (현행과 같음)\n",
  "sections": {
    "제안이유": "및",
    "주요내용": "현행법은 군인이 안정된 주거생활을 함으로써 근무에 전념할 수 있\n도록 군인에게 군 숙소인 관사(부양가족이 있는 경우) 또는 간부숙소\n(부양가족이 없는 군인)와 같은 주거지원을 제공하도록 규정하고 있\n음.\n그런데 부양가족이 없는 초급간부 등의 경우에는 관사 입주자격이\n없기에 주로 간부숙소에 입주하며, 만약 간부숙소가 없거나 부족한 경\n우에는 개인부담으로 전ㆍ월세 자금을 마련하여 거주하는 실정임.\n이에 간부숙소 부족으로 주거지원을 받지 못하는 초급간부 등에게\n전ㆍ월세를 지원받게 하도록 관련 규정을 개정해 주거지원 사각지대\n를 해소하고자 함.\n또한 현행 「군인복지기본법」 제9조제1항제1호에 군 숙소를 ‘관사\n또는 독신자숙소’로 규정하고 있음. 독신자숙소에서 ‘독신’은 배우자가\n\n\n\n없는 사람을 지칭하는 것임. 그러나 기혼자 중 근무지가 원거리로 인\n해 가족과 떨어져 사는 군인의 경우 독신이 아님에도 독신자숙소에\n거주하기 때문에 ‘기혼독신자숙소’라는 명칭으로 운영해왔음.\n‘미혼’, ‘기혼’, ‘독신’이라는 명칭을 혼합해 사용해온 모순을 해소하기\n위해 지난 2009년 「국방ㆍ군사시설기준」에서 사용되던 ‘독신자숙소’\n는 ‘간부숙소’로 명칭이 수정된 바 있음. 또한, 군인 주거지원 관련 훈\n령인 「군 주거지원 사업 운영 훈령」에서는 2014년부터 독신숙소를\n간부숙소로 변경해 운영해왔음.\n따라서 이에 맞춰 군 주거지원의 근거법령인 「군인복지기본법」에\n규정되어 있는 독신자숙소를 간부숙소로 용어를 수정하고자 함(안 제9\n조제1항).",
    "제안이유_및_주요내용": "현행법은 군인이 안정된 주거생활을 함으로써 근무에 전념할 수 있\n도록 군인에게 군 숙소인 관사(부양가족이 있는 경우) 또는 간부숙소\n(부양가족이 없는 군인)와 같은 주거지원을 제공하도록 규정하고 있\n음.\n그런데 부양가족이 없는 초급간부 등의 경우에는 관사 입주자격이\n없기에 주로 간부숙소에 입주하며, 만약 간부숙소가 없거나 부족한 경\n우에는 개인부담으로 전ㆍ월세 자금을 마련하여 거주하는 실정임.\n이에 간부숙소 부족으로 주거지원을 받지 못하는 초급간부 등에게\n전ㆍ월세를 지원받게 하도록 관련 규정을 개정해 주거지원 사각지대\n를 해소하고자 함.\n또한 현행 「군인복지기본법」 제9조제1항제1호에 군 숙소를 ‘관사\n또는 독신자숙소’로 규정하고 있음. 독신자숙소에서 ‘독신’은 배우자가\n\n\n\n없는 사람을 지칭하는 것임. 그러나 기혼자 중 근무지가 원거리로 인\n해 가족과 떨어져 사는 군인의 경우 독신이 아님에도 독신자숙소에\n거주하기 때문에 ‘기혼독신자숙소’라는 명칭으로 운영해왔음.\n‘미혼’, ‘기혼’, ‘독신’이라는 명칭을 혼합해 사용해온 모순을 해소하기\n위해 지난 2009년 「국방ㆍ군사시설기준」에서 사용되던 ‘독신자숙소’\n는 ‘간부숙소’로 명칭이 수정된 바 있음. 또한, 군인 주거지원 관련 훈\n령인 「군 주거지원 사업 운영 훈령」에서는 2014년부터 독신숙소를\n간부숙소로 변경해 운영해왔음.\n따라서 이에 맞춰 군 주거지원의 근거법령인 「군인복지기본법」에\n규정되어 있는 독신자숙소를 간부숙소로 용어를 수정하고자 함(안 제9\n조제1항).",
    "법률_제_호": "군인복지기본법 일부개정법률안\n군인복지기본법 일부를 다음과 같이 개정한다.\n제9조제1항 각 호 외의 부분 단서 중 “관사를 제공받지 못한 군인에”\n를 “군 숙소를 제공받지 못한 군인에”로 하고, 같은 항 제1호 중 “관\n사 또는 독신자숙소”를 “관사 또는 간부숙소”로 한다.",
    "신구조문대비표": "현 행 개 정 안\n제9조(군 숙소 지원 등) ① 국가 제9조(군 숙소 지원 등) ① ----\n는 군인이 안정된 주거생활을 -------------------------\n함으로써 근무에 전념할 수 있 -------------------------\n도록 하기 위하여 군인(지원에 -------------------------\n의하지 아니하고 임용된 부사 -------------------------\n관 및 병을 제외한다. 이하 이 -------------------------\n조 및 제10조에서 같다)에게 -------------------------\n다음 각 호의 어느 하나에 해 -------------------------\n당하는 주거지원을 제공하여야 -------------------------\n한다. 다만, 제2호에 해당하는 ----. -------------------\n주거지원은 관사를 제공받지 ---------군 숙소를 제공받지\n못한 군인에 한하여 제공한다. 못한 군인에--------------.\n1. 관사 또는 독신자숙소(이하 1. 관사 또는 간부숙소-------\n이 조에서 “군 숙소”라 한다) -----------------------\n2. (생 략) 2. (현행과 같음)\n② ∼ ④ (생 략) ② ∼ ④ (현행과 같음)"
  }
}