{
  "title": "2207217_조세특례제한법_일부개정법률안",
  "bill_number": "7217",
  "proposal_date": "2025. 1. 3.",
  "submission_date": "",
  "is_alternative": false,
  "alternative_bill_numbers": [],
  "has_comparison_table": false,
  "comparison_table": "신ㆍ구조문대비표\n현 행 개 정 안\n제92조(혼인에 대한 세액공제) ① 제92조(혼인에 대한 세액공제) ①\n거주자가 2026년 12월 31일 이 ---------2027년-------------\n전에 혼인신고를 한 경우에는 ----------------------------\n1회(혼인신고 후 그 혼인이 무 ----------------------------\n효가 되어 제2항에 따른 신고 ----------------------------\n를 한 경우는 제외한다)에 한 ----------------------------\n정하여 혼인신고를 한 날이 속 ----------------------------\n하는 과세기간의 종합소득산출 ----------------------------\n세액에서 50만원을 공제한다. -------300만원-----------.\n②ㆍ③ (생 략) ②ㆍ③ (현행과 같음)",
  "full_text": "조세특례제한법 일부개정법률안\n(송석준의원 대표발의)\n발의연월일 : 2025. 1. 3.\n의 안\n7217\n번 호 발 의 자 : 송석준ㆍ김선교ㆍ김성원\n김예지ㆍ이종배ㆍ박형수\n윤상현ㆍ박덕흠ㆍ조배숙\n주진우ㆍ유상범ㆍ김미애\n장동혁ㆍ이헌승 의원\n(14인)\n제안이유 및 주요내용\n출산율 제고의 전제라 할 수 있는 혼인건수는 지속적으로 감소하여\n2021년 처음 20만건 이하로 집계되었고, 2023년 기준 19만3,657건까지\n추락했음. 덩달아 출생아 수도 지속적으로 감소하여 2016년 약 40만\n6,000명에서 2023년 23만명으로까지 감소하여 합계출산율은 2023년 기\n준 0.72로 역대 최저치에 맴돌고 있음.\n우리 국민들이 혼인을 하지 않는 가장 큰 사유로는 남녀 모두 결혼\n자금의 부족(남자 35.4%, 여자 22.0%)을 들고 있음(2022년 통계청 조\n사).\n그런데 작년 혼인에 대한 종합소득산출세액에서 세액공제를 도입하\n였으나 그 기한을 2026년말로 한정하였고, 세액공제금액도 50만원에\n불과하여 낮아질 대로 낮아진 저출생 문제와 신혼부부의 재정적 부담\n\n\n\n을 경감하는데 미흡하다는 지적이 존재함.\n이에 혼인신고를 한 신혼부부 세액공제 금액을 기존 50만원에서\n300만원으로 확대하고, 2027년말까지 세액공제제도를 연장함으로써 혼\n인을 장려하고 저출생 문제해소에 실질적인 도움을 주려는 것임(안 제\n92조).\n\n법률 제 호\n조세특례제한법 일부개정법률안\n조세특례제한법 일부를 다음과 같이 개정한다.\n제92조제1항 중 “2026년”을 “2027년”으로, “50만원”을 “300만원”으로\n한다.\n부 칙\n제1조(시행일) 이 법은 2026년 1월 1일부터 시행한다.\n제2조(혼인에 대한 세액공제에 관한 적용례) 제92조의 개정규정은 이\n법 시행 이후 종합소득과세표준 확정신고를 하거나 연말정산하는\n경우부터 적용한다.\n\n\n\n\n신ㆍ구조문대비표\n현 행 개 정 안\n제92조(혼인에 대한 세액공제) ① 제92조(혼인에 대한 세액공제) ①\n거주자가 2026년 12월 31일 이 ---------2027년-------------\n전에 혼인신고를 한 경우에는 ----------------------------\n1회(혼인신고 후 그 혼인이 무 ----------------------------\n효가 되어 제2항에 따른 신고 ----------------------------\n를 한 경우는 제외한다)에 한 ----------------------------\n정하여 혼인신고를 한 날이 속 ----------------------------\n하는 과세기간의 종합소득산출 ----------------------------\n세액에서 50만원을 공제한다. -------300만원-----------.\n②ㆍ③ (생 략) ②ㆍ③ (현행과 같음)\n",
  "sections": {
    "제안이유": "및",
    "주요내용": "출산율 제고의 전제라 할 수 있는 혼인건수는 지속적으로 감소하여\n2021년 처음 20만건 이하로 집계되었고, 2023년 기준 19만3,657건까지\n추락했음. 덩달아 출생아 수도 지속적으로 감소하여 2016년 약 40만\n6,000명에서 2023년 23만명으로까지 감소하여 합계출산율은 2023년 기\n준 0.72로 역대 최저치에 맴돌고 있음.\n우리 국민들이 혼인을 하지 않는 가장 큰 사유로는 남녀 모두 결혼\n자금의 부족(남자 35.4%, 여자 22.0%)을 들고 있음(2022년 통계청 조\n사).\n그런데 작년 혼인에 대한 종합소득산출세액에서 세액공제를 도입하\n였으나 그 기한을 2026년말로 한정하였고, 세액공제금액도 50만원에\n불과하여 낮아질 대로 낮아진 저출생 문제와 신혼부부의 재정적 부담\n\n\n\n을 경감하는데 미흡하다는 지적이 존재함.\n이에 혼인신고를 한 신혼부부 세액공제 금액을 기존 50만원에서\n300만원으로 확대하고, 2027년말까지 세액공제제도를 연장함으로써 혼\n인을 장려하고 저출생 문제해소에 실질적인 도움을 주려는 것임(안 제\n92조).",
    "제안이유_및_주요내용": "출산율 제고의 전제라 할 수 있는 혼인건수는 지속적으로 감소하여\n2021년 처음 20만건 이하로 집계되었고, 2023년 기준 19만3,657건까지\n추락했음. 덩달아 출생아 수도 지속적으로 감소하여 2016년 약 40만\n6,000명에서 2023년 23만명으로까지 감소하여 합계출산율은 2023년 기\n준 0.72로 역대 최저치에 맴돌고 있음.\n우리 국민들이 혼인을 하지 않는 가장 큰 사유로는 남녀 모두 결혼\n자금의 부족(남자 35.4%, 여자 22.0%)을 들고 있음(2022년 통계청 조\n사).\n그런데 작년 혼인에 대한 종합소득산출세액에서 세액공제를 도입하\n였으나 그 기한을 2026년말로 한정하였고, 세액공제금액도 50만원에\n불과하여 낮아질 대로 낮아진 저출생 문제와 신혼부부의 재정적 부담\n\n\n\n을 경감하는데 미흡하다는 지적이 존재함.\n이에 혼인신고를 한 신혼부부 세액공제 금액을 기존 50만원에서\n300만원으로 확대하고, 2027년말까지 세액공제제도를 연장함으로써 혼\n인을 장려하고 저출생 문제해소에 실질적인 도움을 주려는 것임(안 제\n92조).",
    "법률_제_호": "조세특례제한법 일부개정법률안\n조세특례제한법 일부를 다음과 같이 개정한다.\n제92조제1항 중 “2026년”을 “2027년”으로, “50만원”을 “300만원”으로\n한다.",
    "신구조문대비표": "현 행 개 정 안\n제92조(혼인에 대한 세액공제) ① 제92조(혼인에 대한 세액공제) ①\n거주자가 2026년 12월 31일 이 ---------2027년-------------\n전에 혼인신고를 한 경우에는 ----------------------------\n1회(혼인신고 후 그 혼인이 무 ----------------------------\n효가 되어 제2항에 따른 신고 ----------------------------\n를 한 경우는 제외한다)에 한 ----------------------------\n정하여 혼인신고를 한 날이 속 ----------------------------\n하는 과세기간의 종합소득산출 ----------------------------\n세액에서 50만원을 공제한다. -------300만원-----------.\n②ㆍ③ (생 략) ②ㆍ③ (현행과 같음)"
  }
}