{
  "title": "2208660_공직선거법_일부개정법률안",
  "bill_number": "8660",
  "proposal_date": "2025. 3. 5.",
  "submission_date": "",
  "is_alternative": false,
  "alternative_bill_numbers": [],
  "has_comparison_table": false,
  "comparison_table": "신ㆍ구조문대비표\n현 행 개 정 안\n제60조(선거운동을 할 수 없는 제60조(선거운동을 할 수 없는\n자) ① 다음 각 호의 어느 하 자) ① ---------------------\n나에 해당하는 사람은 선거운 ----------------------------\n동을 할 수 없다. 다만, 제1호 -------------. --------------\n에 해당하는 사람이 예비후보 ----------------------------\n자ㆍ후보자의 배우자인 경우와 ----------------------------\n제4호부터 제8호까지의 규정에 ----------------------------\n해당하는 사람이 예비후보자ㆍ ----------------------------\n후보자의 배우자이거나 후보자 ----------------------------\n의 직계존비속인 경우에는 그 ----------------------------\n러하지 아니하다. --------------.\n1. ∼ 4. (생 략) 1. ∼ 4. (현행과 같음)\n5. 第53條(公務員 등의 立候補) 5. 제53조제1항제2호부터 제7호\n第1項第2號 내지 제7호에 해 까지에 해당하는 사람\n당하는 者(제5호의 경우에는\n그 常勤職員을 포함한다)\n6. ∼ 9. (생 략) 6. ∼ 9. (현행과 같음)\n② (생 략) ② (현행과 같음)",
  "full_text": "공직선거법 일부개정법률안\n(전종덕의원 대표발의)\n발의연월일 : 2025. 3. 5.\n의 안\n8660\n번 호 발 의 자 : 전종덕ㆍ정혜경ㆍ김 윤\n용혜인ㆍ송옥주ㆍ이수진\n송재봉ㆍ윤종오ㆍ박정현\n한창민ㆍ김종민 의원\n(11인)\n제안이유 및 주요내용\n현행법은 「농업협동조합법」, 「수산업협동조합법」, 「산림조합\n법」, 「엽연초생산협동조합법」에 의해 설립된 조합의 상근 임원과\n이들 조합의 중앙회장의 경우 입후보하려면 선거일 전 90일까지 그\n직을 그만두도록 하고, 이들을 비롯하여 해당 조합의 상근직원은 선거\n운동을 금지하고 있음.\n그런데 협동조합의 상근직원이 수행하는 직무의 내용ㆍ영향력 및\n책임성 등을 고려하면 이들의 선거운동을 제한하는 것은 그 필요성에\n비하여 선거운동의 자유를 과도하게 침해한다는 지적이 계속 제기되\n었고, 최근에는 비슷한 취지로 지방공사ㆍ공단 상근직원의 선거운동\n금지 규정을 삭제하는 입법이 이루어진 바 있음.\n이에, 협동조합의 상근직원의 선거운동을 제한하는 규정을 삭제하여\n\n\n\n선거운동의 자유를 보장하려는 것임(안 제60조제1항제5호).\n\n법률 제 호\n공직선거법 일부개정법률안\n공직선거법 일부를 다음과 같이 개정한다.\n제60조제1항제5호를 다음과 같이 한다.\n5. 제53조제1항제2호부터 제7호까지에 해당하는 사람\n부 칙\n이 법은 공포한 날부터 시행한다.\n\n\n\n\n신ㆍ구조문대비표\n현 행 개 정 안\n제60조(선거운동을 할 수 없는 제60조(선거운동을 할 수 없는\n자) ① 다음 각 호의 어느 하 자) ① ---------------------\n나에 해당하는 사람은 선거운 ----------------------------\n동을 할 수 없다. 다만, 제1호 -------------. --------------\n에 해당하는 사람이 예비후보 ----------------------------\n자ㆍ후보자의 배우자인 경우와 ----------------------------\n제4호부터 제8호까지의 규정에 ----------------------------\n해당하는 사람이 예비후보자ㆍ ----------------------------\n후보자의 배우자이거나 후보자 ----------------------------\n의 직계존비속인 경우에는 그 ----------------------------\n러하지 아니하다. --------------.\n1. ∼ 4. (생 략) 1. ∼ 4. (현행과 같음)\n5. 第53條(公務員 등의 立候補) 5. 제53조제1항제2호부터 제7호\n第1項第2號 내지 제7호에 해 까지에 해당하는 사람\n당하는 者(제5호의 경우에는\n그 常勤職員을 포함한다)\n6. ∼ 9. (생 략) 6. ∼ 9. (현행과 같음)\n② (생 략) ② (현행과 같음)\n",
  "sections": {
    "제안이유": "및",
    "주요내용": "현행법은 「농업협동조합법」, 「수산업협동조합법」, 「산림조합\n법」, 「엽연초생산협동조합법」에 의해 설립된 조합의 상근 임원과\n이들 조합의 중앙회장의 경우 입후보하려면 선거일 전 90일까지 그\n직을 그만두도록 하고, 이들을 비롯하여 해당 조합의 상근직원은 선거\n운동을 금지하고 있음.\n그런데 협동조합의 상근직원이 수행하는 직무의 내용ㆍ영향력 및\n책임성 등을 고려하면 이들의 선거운동을 제한하는 것은 그 필요성에\n비하여 선거운동의 자유를 과도하게 침해한다는 지적이 계속 제기되\n었고, 최근에는 비슷한 취지로 지방공사ㆍ공단 상근직원의 선거운동\n금지 규정을 삭제하는 입법이 이루어진 바 있음.\n이에, 협동조합의 상근직원의 선거운동을 제한하는 규정을 삭제하여\n\n\n\n선거운동의 자유를 보장하려는 것임(안 제60조제1항제5호).",
    "제안이유_및_주요내용": "현행법은 「농업협동조합법」, 「수산업협동조합법」, 「산림조합\n법」, 「엽연초생산협동조합법」에 의해 설립된 조합의 상근 임원과\n이들 조합의 중앙회장의 경우 입후보하려면 선거일 전 90일까지 그\n직을 그만두도록 하고, 이들을 비롯하여 해당 조합의 상근직원은 선거\n운동을 금지하고 있음.\n그런데 협동조합의 상근직원이 수행하는 직무의 내용ㆍ영향력 및\n책임성 등을 고려하면 이들의 선거운동을 제한하는 것은 그 필요성에\n비하여 선거운동의 자유를 과도하게 침해한다는 지적이 계속 제기되\n었고, 최근에는 비슷한 취지로 지방공사ㆍ공단 상근직원의 선거운동\n금지 규정을 삭제하는 입법이 이루어진 바 있음.\n이에, 협동조합의 상근직원의 선거운동을 제한하는 규정을 삭제하여\n\n\n\n선거운동의 자유를 보장하려는 것임(안 제60조제1항제5호).",
    "법률_제_호": "공직선거법 일부개정법률안\n공직선거법 일부를 다음과 같이 개정한다.\n제60조제1항제5호를 다음과 같이 한다.\n5. 제53조제1항제2호부터 제7호까지에 해당하는 사람",
    "신구조문대비표": "현 행 개 정 안\n제60조(선거운동을 할 수 없는 제60조(선거운동을 할 수 없는\n자) ① 다음 각 호의 어느 하 자) ① ---------------------\n나에 해당하는 사람은 선거운 ----------------------------\n동을 할 수 없다. 다만, 제1호 -------------. --------------\n에 해당하는 사람이 예비후보 ----------------------------\n자ㆍ후보자의 배우자인 경우와 ----------------------------\n제4호부터 제8호까지의 규정에 ----------------------------\n해당하는 사람이 예비후보자ㆍ ----------------------------\n후보자의 배우자이거나 후보자 ----------------------------\n의 직계존비속인 경우에는 그 ----------------------------\n러하지 아니하다. --------------.\n1. ∼ 4. (생 략) 1. ∼ 4. (현행과 같음)\n5. 第53條(公務員 등의 立候補) 5. 제53조제1항제2호부터 제7호\n第1項第2號 내지 제7호에 해 까지에 해당하는 사람\n당하는 者(제5호의 경우에는\n그 常勤職員을 포함한다)\n6. ∼ 9. (생 략) 6. ∼ 9. (현행과 같음)\n② (생 략) ② (현행과 같음)"
  }
}